{
  "id": "guide-winter-tips",
  "tier": 2,
  "type": "guide",
  "slug": "winter-travel-tips",
  "lang": "ru",
  "title": "Зимний отдых: советы",
  "subtitle": "Как подготовиться к зимнему путешествию",
  "summary": "Практические советы для зимнего отдыха в Сочи и Абхазии — что взять, как одеться, где согреться.",
  "emoji": "❄️",
  "heroImage": "https://images.unsplash.com/photo-1517299321609-52687d1bc55a?w=800&q=80",
  "highlights": ["Многослойная одежда", "Тёплая обувь", "Термос с чаем", "Горнолыжное снаряжение"],
  "meta": {
    "tags": ["зимний отдых", "советы туристам", "горные лыжи"],
    "category": "practical"
  },
  "content": "## Советы для зимнего отдыха\n\n### Одежда\n- Многослойность: термобельё + флис + мембрана\n- Тёплая непромокаемая обувь\n- Перчатки, шапка, шарф\n\n### В горы\n- Солнцезащитные очки (снег отражает УФ)\n- Крем SPF 30+\n- Термос с горячим чаем\n\n### На экскурсии\n- Удобная обувь с нескользящей подошвой\n- Пауэрбанк для телефона (холод разряжает)",
  "metadata": { "created": "2025-12-04", "updated": "2025-12-04", "version": "2.0.0", "author": "ApsnyTravel" }
}
